{
  "id": "slide-151",
  "slide_number": 151,
  "title": "Subtitle",
  "content": "YOUR TITLE",
  "bullet_points": [
    "Lorem ipsum dolor sit amet, consectetur adipiscing elit. Sed eget.",
    "YOUR TITLE",
    "Lorem ipsum dolor sit amet, consectetur adipiscing elit. Sed eget.",
    "YOUR TITLE",
    "Lorem ipsum dolor sit amet, consectetur adipiscing elit. Sed eget.",
    "YOUR TITLE",
    "Lorem ipsum dolor sit amet, consectetur adipiscing elit. Sed eget.",
    "YOUR TITLE",
    "Lorem ipsum dolor sit amet, consectetur adipiscing elit. Sed eget.",
    "Week 1",
    "Week 2",
    "Week 3",
    "Week 4",
    "Week 5",
    "Week 6",
    "Week 7",
    "Week 8",
    "Week 9",
    "Week 10",
    "Week 11",
    "Week 12",
    "Template — High-level Workplan"
  ],
  "has_image": false,
  "has_chart": false,
  "has_table": false,
  "layout_name": "OK_content",
  "text_content": [
    "Subtitle",
    "YOUR TITLE",
    "Lorem ipsum dolor sit amet, consectetur adipiscing elit. Sed eget.",
    "YOUR TITLE",
    "Lorem ipsum dolor sit amet, consectetur adipiscing elit. Sed eget.",
    "YOUR TITLE",
    "Lorem ipsum dolor sit amet, consectetur adipiscing elit. Sed eget.",
    "YOUR TITLE",
    "Lorem ipsum dolor sit amet, consectetur adipiscing elit. Sed eget.",
    "YOUR TITLE",
    "Lorem ipsum dolor sit amet, consectetur adipiscing elit. Sed eget.",
    "Week 1",
    "Week 2",
    "Week 3",
    "Week 4",
    "Week 5",
    "Week 6",
    "Week 7",
    "Week 8",
    "Week 9",
    "Week 10",
    "Week 11",
    "Week 12",
    "Template — High-level Workplan"
  ],
  "shape_count": 44,
  "design_elements": {
    "text_blocks": 24,
    "visual_elements": 0,
    "color_usage": "unknown",
    "layout_complexity": "complex"
  },
  "image_filename": "slide_151.png",
  "image_path": "images/slide_151.png"
}